mastercardmdescustomerservice/__init__.py
mastercardmdescustomerservice/accountholdermessaging.py
mastercardmdescustomerservice/resourceconfig.py
mastercardmdescustomerservice/search.py
mastercardmdescustomerservice/systemstatus.py
mastercardmdescustomerservice/tokenactivate.py
mastercardmdescustomerservice/tokenactivationmethods.py
mastercardmdescustomerservice/tokencomments.py
mastercardmdescustomerservice/tokendelete.py
mastercardmdescustomerservice/tokenresendactivationcode.py
mastercardmdescustomerservice/tokenresetmobilepin.py
mastercardmdescustomerservice/tokenstatushistory.py
mastercardmdescustomerservice/tokensuspend.py
mastercardmdescustomerservice/tokenunsuspend.py
mastercardmdescustomerservice/tokenupdate.py
mastercardmdescustomerservice/transactions.py
mastercardmdescustomerservice/updatetokenassurance.py
mastercard_mdes_customer_service-2.0.8.dist-info/LICENSE
mastercard_mdes_customer_service-2.0.8.dist-info/METADATA
mastercard_mdes_customer_service-2.0.8.dist-info/WHEEL
mastercard_mdes_customer_service-2.0.8.dist-info/top_level.txt
mastercard_mdes_customer_service-2.0.8.dist-info/RECORD
